{
  "db_name": "PostgreSQL",
  "query": "\n        INSERT INTO transaction (id, created_at, type, amount, currency, processor,\n            project_id, customer_id, product_id, product_price_id,\n            checkout_session_id, charge_id, succeeded_at)\n        VALUES ($1, NOW(), 'payment', $2, $3, $4, $5, $6, $7, $8, $9, $10, NOW())\n        ",
  "describe": {
    "columns": [],
    "parameters": {
      "Left": [
        "Uuid",
        "Int8",
        "Varchar",
        "Text",
        "Uuid",
        "Uuid",
        "Uuid",
        "Uuid",
        "Uuid",
        "Text"
      ]
    },
    "nullable": []
  },
  "hash": "f6fb6493a1c1f541b4cca069d5d1bff7fc183f93eb0f8ede45125f0cdbeb1487"
}
